vogmidea/__init__.py
vogmidea/base_device.py
vogmidea/cli.py
vogmidea/cloud.py
vogmidea/const.py
vogmidea/crc8.py
vogmidea/discover.py
vogmidea/frame.py
vogmidea/lan.py
vogmidea/utils.py
vogmidea/device/__init__.py
vogmidea/device/AC/__init__.py
vogmidea/device/AC/command.py
vogmidea/device/AC/device.py
vogmidea/device/AC/test_command.py
vogmidea/device/AC/test_device.py
vogmidea-0.1.2.dist-info/LICENSE.md
vogmidea-0.1.2.dist-info/METADATA
vogmidea-0.1.2.dist-info/WHEEL
vogmidea-0.1.2.dist-info/entry_points.txt
vogmidea-0.1.2.dist-info/top_level.txt
vogmidea-0.1.2.dist-info/RECORD
