Metadata-Version: 2.1
Name: vogmidea
Version: 0.1.2
Summary: A Python library for local control of Midea (and associated brands) smart air conditioners. !! THIS IS A DEVELOPMENT PROJECT !! For the original, please refer to https://github.com/mill1000/midea-msmart
Author-email: Stephen Davis <sdavis@nativeit.net>
License: MIT
Project-URL: Repository, https://github.com/vogsphe-re/midea-msmart
Project-URL: Issues, https://github.com/vogsphe-re/midea-msmart/issues
Classifier: Programming Language :: Python :: 3
Classifier: Programming Language :: Python :: 3.8
Classifier: Programming Language :: Python :: 3.9
Classifier: Programming Language :: Python :: 3.10
Classifier: Programming Language :: Python :: 3.11
Classifier: Programming Language :: Python :: 3.12
Classifier: License :: OSI Approved :: MIT License
Classifier: Operating System :: OS Independent
Classifier: Topic :: Home Automation
Requires-Python: >=3.8
License-File: LICENSE.md
Requires-Dist: pycryptodome
Requires-Dist: httpx
